func3_lib/__init__.py
func3_lib/func3_lib.egg-info/dependency_links.txt
func3_lib/func3_lib.egg-info/PKG-INFO
func3_lib/func3_lib.egg-info/requires.txt
func3_lib/func3_lib.egg-info/SOURCES.txt
func3_lib/func3_lib.egg-info/top_level.txt
func3_lib/func3_lt.py
func3_lib/README.md
func3_lib/tests/__init__.py
func3_lib/tests/test_convolution2d.py
func3_lib/tests/test_manual.ipynb
func3_lib/tests/test_transpose2d.py
func3_lib/tests/test_window1d.py
func3_lib-0.0.2.dist-info/LICENSE.txt
func3_lib-0.0.2.dist-info/METADATA
func3_lib-0.0.2.dist-info/WHEEL
func3_lib-0.0.2.dist-info/RECORD
