Metadata-Version: 2.1
Name: func3_lib
Version: 0.0.2
Summary: Three functions func3_lib 'transpose2d', 'window1d' and 'convolution2d'.
License: MIT
Author: LinasT
Requires-Python: >=3.10,<4.0
Classifier: License :: OSI Approved :: MIT License
Classifier: Programming Language :: Python :: 3
Classifier: Programming Language :: Python :: 3.10
Classifier: Programming Language :: Python :: 3.11
Classifier: Programming Language :: Python :: 3.12
Requires-Dist: numpy (>=1.26.2,<2.0.0)
Requires-Dist: pytest (>=7.4.3,<8.0.0)
Requires-Dist: pytest-cov (>=4.1.0,<5.0.0)
Requires-Dist: setuptools (>=68.2.2,<69.0.0)
Requires-Dist: twine (>=4.0.2,<5.0.0)
Requires-Dist: wheel (>=0.41.3,<0.42.0)
